t_screenwise
