Metadata-Version: 2.2
Name: t_screenwise
Version: 1.0.1
Summary: A Python package for detecting and interacting with screen elements using computer vision and OCR.
Home-page: https://www.thoughtful.ai/
Author: Nikolas Cohn, Alejandro Muñoz
Author-email: support@thoughtful.ai
Keywords: t_screenwise
Classifier: Intended Audience :: Developers
Classifier: Natural Language :: English
Classifier: Programming Language :: Python :: 3
Classifier: Programming Language :: Python :: 3.9
Requires-Python: >=3.9
Requires-Dist: numpy<2
Requires-Dist: matplotlib
Requires-Dist: pyautogui
Requires-Dist: requests
Requires-Dist: retry
Dynamic: author
Dynamic: author-email
Dynamic: classifier
Dynamic: description
Dynamic: description-content-type
Dynamic: home-page
Dynamic: keywords
Dynamic: requires-dist
Dynamic: requires-python
Dynamic: summary
